scie2g/__init__.py
scie2g/__main__.py
scie2g/base.py
scie2g/bed.py
scie2g/csv.py
scie2g/errors.py
scie2g-1.0.3.data/data/LICENSE
scie2g-1.0.3.dist-info/LICENSE
scie2g-1.0.3.dist-info/METADATA
scie2g-1.0.3.dist-info/WHEEL
scie2g-1.0.3.dist-info/entry_points.txt
scie2g-1.0.3.dist-info/top_level.txt
scie2g-1.0.3.dist-info/RECORD
