Metadata-Version: 2.1
Name: scie2g
Version: 1.0.3
Summary: UNKNOWN
Home-page: https://github.com/ArianeMora/sciepi2gene
Author: Ariane Mora
Author-email: ariane.n.mora@gmail.com
License: GPL3
Project-URL: Bug Tracker, https://github.com/ArianeMora/sciepi2gene/issues
Project-URL: Documentation, https://github.com/ArianeMora/sciepi2gene
Project-URL: Source Code, https://github.com/ArianeMora/sciepi2gene
Keywords: epigenetics,bioinformatics
Platform: UNKNOWN
Classifier: Intended Audience :: Science/Research
Classifier: License :: OSI Approved :: GNU General Public License v3 (GPLv3)
Classifier: Natural Language :: English
Classifier: Operating System :: OS Independent
Classifier: Programming Language :: Python :: 3.6
Classifier: Programming Language :: Python :: 3.7
Classifier: Programming Language :: Python :: 3.8
Classifier: Topic :: Scientific/Engineering :: Bio-Informatics
Requires-Python: >=3.6
Requires-Dist: pandas
Requires-Dist: numpy
Requires-Dist: scibiomart
Requires-Dist: sciutil (>=1.0.3)
Requires-Dist: tqdm
Requires-Dist: igv-jupyter
